differentiator.v
module differentiator #(
    parameter N=2, 
    parameter BITS=10
) (
    input clk, 
    input rst, 
    input [BITS-1:0] stream_in, 
    input valid,
    output reg [BITS-1:0] stream_out, 
    output reg ready
);

    localparam N_BITS = $clog2(N);

    integer i;
    
    reg [BITS-1:0] buffer [N-1:0];
    reg [BITS-1:0] value;
    reg [N_BITS-1:0] pointer;
    
    always @(posedge clk) begin
        if (rst) begin
            stream_out <= 0;
            pointer <= 0;
            ready <= 0;
            for (i = 0; i < N; i = i + 1) begin
                buffer[i] <= 0;
            end
        end else if (valid) begin
            value = stream_in - buffer[pointer];
            stream_out <= value[BITS-1:N_BITS];
            buffer[pointer] <= stream_in;
            pointer <= pointer + 1 == N ? 0 : pointer + 1;
            ready <= 1;
        end else begin
            ready <= 0;
        end
    end

endmodule

comb.v
module comb #(
    parameter M=1,
    parameter N=2,
    parameter BITS=10
) (
    input clk, 
    input rst, 
    input [BITS-1:0] stream_in, 
    input valid,
    output [BITS-1:0] stream_out, 
    output ready
);
    wire [BITS-1:0] data [M:0];
    wire handshake [M:0];

    genvar m;
    generate
        for (m = 0; m < M; m = m + 1) begin
            differentiator #(
                .N(N), 
                .BITS(BITS)
            ) dt (
                .clk(clk), 
                .rst(rst), 
                .stream_in(data[m]),
                .valid(handshake[m]),
                .stream_out(data[m + 1]),
                .ready(handshake[m + 1])
            );
        end
    endgenerate

    assign data[0] = stream_in;
    assign handshake[0] = valid;
    assign stream_out = data[M];
    assign ready = handshake[M];

endmodule

downsampler.v
module downsampler #(
    parameter N=2, 
    parameter BITS=10, 
    parameter N_BITS=$clog2(N)+1
) (
    input clk, 
    input rst,
    input [BITS-1:0] stream_in, 
    input valid,
    output reg [BITS-1:0] stream_out, 
    output reg ready
);
    reg [N_BITS-1:0] sample;
    
    always @(posedge clk) begin
        if (rst) begin
            sample <= 0;
            stream_out <= 0;
            ready <= 0;
        end 

        if (valid) begin
            if (sample == 0) begin
                stream_out <= stream_in;
                ready <= 1;
            end else ready <= 0;
            sample <= sample + 1 == N ? 0 : sample + 1;
        end else begin
            ready <= 0;
        end
    end
        
endmodule

integrator.v
module integrator #(
    parameter BITS=10
) (
    input clk, 
    input rst, 
    input [BITS-1:0] stream_in, 
    input valid,
    output [BITS-1:0] stream_out, 
    output reg ready
); 

    reg [BITS-1:0] buffer;

    always @(posedge clk) begin
        if (rst) begin
            buffer <= 0;
            ready <= 0;
        end else if (valid) begin
            buffer <= stream_in + buffer;
            ready <= 1;
        end
    end

    assign stream_out = buffer;

endmodule

accumulator.v
module accumulator #(
    parameter M=1,
    parameter BITS=10
) (
    input clk, 
    input rst, 
    input [BITS-1:0] stream_in, 
    input valid,
    output [BITS-1:0] stream_out, 
    output ready
);
    wire [BITS-1:0] data [M:0];
    wire handshake [M:0];

    genvar m;
    generate 
        for (m = 0; m < M; m = m + 1) begin
            integrator #(
                .BITS(BITS)
            ) it (
                .clk(clk), 
                .rst(rst), 
                .stream_in(data[m]),
                .valid(handshake[m]),
                .stream_out(data[m + 1]),
                .ready(handshake[m + 1])
            );
        end
    endgenerate

    assign data[0] = stream_in;
    assign handshake[0] = valid;
    assign stream_out = data[M];
    assign ready = handshake[M];

endmodule

CIC.v
module CIC #(
    parameter M=1, 
    parameter N=2, 
    parameter BITS=10,
    parameter N_BITS=$clog2(N)
) (
    input clk, 
    input rst, 
    input [BITS-1:0] stream_in, 
    input valid,
    output [BITS-1:0] stream_out, 
    output ready
);

    wire [BITS-1:0] accumulated;
    wire accumulated_ready;
    wire [BITS-1:0] downsampled;
    wire downsampled_ready;

    accumulator #(
        .M(M),
        .BITS(BITS)
    ) accumulator (
        .clk(clk),
        .rst(rst),
        .stream_in(stream_in),
        .valid(valid),
        .stream_out(accumulated),
        .ready(accumulated_ready)
    );

    downsampler #(
        .N(N),
        .BITS(BITS)
    ) downsampler (
        .clk(clk),
        .rst(rst),
        .stream_in(accumulated),
        .valid(accumulated_ready),
        .stream_out(downsampled),
        .ready(downsampled_ready)
    );

    differentiator #(
        .N(N),
        .BITS(BITS)
    ) differentiator (
        .clk(clk),
        .rst(rst),
        .stream_in(downsampled),
        .valid(downsampled_ready),
        .stream_out(stream_out),
        .ready(ready)
    );

endmodule

CIC_tb.v
`timescale 1ps/1ps

`define assert(signal, value) \
	if (signal != value) begin \
		$display("ASSERTION FAILED in %m: signal != value"); \
	end


module CIC_tb();

    localparam T = 2;
    localparam N = 2;
    localparam M = 1;
    localparam BITS = 32;

    integer fr, fw;

    reg clk = 0;
    reg rst = 0;
    reg [BITS-1:0] stream_in = 0;
    reg valid = 0;
    wire [BITS-1:0] stream_out;
    wire ready;

    reg [31:0] value = 0;

    CIC #(
        .M(M),
        .N(N),
        .BITS(BITS)
    ) DUT (
        .clk(clk),
        .rst(rst),
        .stream_in(stream_in),
        .valid(valid),
        .stream_out(stream_out),
        .ready(ready)
    );

    initial begin
        clk = 1'b0;
        forever #(T / 2) clk = ~clk;
    end

    initial begin
        rst = 1;
        valid = 0;
        repeat (2) @(posedge clk);
        rst = 0;
        valid = 1;
    end
    
    initial begin
        repeat (2) @(posedge clk)
        fr = $fopen("inputs.txt", "rb");
        while ($fscanf(fr, "%d\n", value)) begin
            stream_in <= value[9:0];
            @(posedge clk);
        end
    end

    initial begin
        repeat (2) @(posedge clk)
        fw = $fopen("outputs.txt", "w");
        while (1) begin
            if (ready) begin 
                $fwrite(fw, "%d\n", stream_out);
            end 
            @(posedge clk);
        end
    end

    initial begin
        $dumpfile("test.vcd");
        $dumpvars;
        #(2 * 1024 *T);
        $finish;
    end

endmodule

test.vcd
$date
	Wed Nov 16 11:48:45 2022
$end
$version
	Icarus Verilog
$end
$timescale
	1ps
$end
$scope module CIC_tb $end
$var wire 32 ! stream_out [31:0] $end
$var wire 1 " ready $end
$var reg 1 # clk $end
$var reg 1 $ rst $end
$var reg 32 % stream_in [31:0] $end
$var reg 1 & valid $end
$var reg 32 ' value [31:0] $end
$var integer 32 ( fr [31:0] $end
$var integer 32 ) fw [31:0] $end
$scope module DUT $end
$var wire 1 # clk $end
$var wire 1 $ rst $end
$var wire 32 * stream_in [31:0] $end
$var wire 1 & valid $end
$var wire 32 + stream_out [31:0] $end
$var wire 1 " ready $end
$var wire 1 , downsampled_ready $end
$var wire 32 - downsampled [31:0] $end
$var wire 1 . accumulated_ready $end
$var wire 32 / accumulated [31:0] $end
$scope module accumulator $end
$var wire 1 # clk $end
$var wire 1 . ready $end
$var wire 1 $ rst $end
$var wire 32 0 stream_in [31:0] $end
$var wire 32 1 stream_out [31:0] $end
$var wire 1 & valid $end
$scope begin genblk1[0] $end
$scope module it $end
$var wire 1 # clk $end
$var wire 1 $ rst $end
$var wire 32 2 stream_in [31:0] $end
$var wire 32 3 stream_out [31:0] $end
$var wire 1 4 valid $end
$var reg 32 5 buffer [31:0] $end
$var reg 1 6 ready $end
$upscope $end
$upscope $end
$upscope $end
$scope module differentiator $end
$var wire 1 # clk $end
$var wire 1 $ rst $end
$var wire 1 , valid $end
$var wire 32 7 stream_in [31:0] $end
$var reg 1 8 pointer $end
$var reg 1 " ready $end
$var reg 32 9 stream_out [31:0] $end
$var reg 32 : value [31:0] $end
$var integer 32 ; i [31:0] $end
$upscope $end
$scope module downsampler $end
$var wire 1 # clk $end
$var wire 1 $ rst $end
$var wire 32 < stream_in [31:0] $end
$var wire 1 . valid $end
$var reg 1 , ready $end
$var reg 2 = sample [1:0] $end
$var reg 32 > stream_out [31:0] $end
$upscope $end
$upscope $end
$upscope $end
$scope module comb $end
$var wire 1 ? clk $end
$var wire 1 @ ready $end
$var wire 1 A rst $end
$var wire 10 B stream_in [9:0] $end
$var wire 10 C stream_out [9:0] $end
$var wire 1 D valid $end
$scope begin genblk1[0] $end
$scope module dt $end
$var wire 1 ? clk $end
$var wire 1 A rst $end
$var wire 10 E stream_in [9:0] $end
$var wire 1 F valid $end
$var reg 1 G pointer $end
$var reg 1 H ready $end
$var reg 10 I stream_out [9:0] $end
$var reg 10 J value [9:0] $end
$var integer 32 K i [31:0] $end
$upscope $end
$upscope $end
$upscope $end
$enddefinitions $end
#0
$dumpvars
bx K
bx J
bx I
xH
xG
zF
bz E
zD
bx C
bz B
zA
x@
z?
bx >
bx =
bx <
bx ;
bx :
bx 9
x8
bx 7
x6
bx 5
04
bx 3
b0 2
bx 1
b0 0
bx /
x.
bx -
x,
bx +
b0 *
bx )
bx (
b0 '
0&
b0 %
1$
0#
x"
bx !
$end
#1
0.
06
b0 /
b0 1
b0 <
b0 3
b0 5
0,
b0 -
b0 7
b0 >
b0 =
0"
08
b0 !
b0 +
b0 9
b10 ;
b10000000000000000000000000000100 (
b10000000000000000000000000000011 )
1#
#2
0#
#3
b1001001111 2
b1001001111 %
b1001001111 *
b1001001111 0
b10000000000000000000000000000110 )
b1001001111 '
b10000000000000000000000000000101 (
14
1&
0$
b10 ;
1#
#4
0#
#5
1.
16
b1001001111 /
b1001001111 1
b1001001111 <
b1001001111 3
b1001001111 5
b1100101111 2
b1100101111 %
b1100101111 *
b1100101111 0
b1100101111 '
1#
#6
0#
#7
b1110110000 2
b1110110000 %
b1110110000 *
b1110110000 0
b1 =
1,
b1001001111 -
b1001001111 7
b1001001111 >
b10101111110 /
b10101111110 1
b10101111110 <
b10101111110 3
b10101111110 5
b1110110000 '
1#
#8
0#
#9
b100100101110 /
b100100101110 1
b100100101110 <
b100100101110 3
b100100101110 5
b0 =
0,
1"
18
b100100111 !
b100100111 +
b100100111 9
b1100000011 2
b1100000011 %
b1100000011 *
b1100000011 0
b1001001111 :
b1100000011 '
1#
#10
0#
#11
b1011110000 2
b1011110000 %
b1011110000 *
b1011110000 0
0"
b1 =
1,
b100100101110 -
b100100101110 7
b100100101110 >
b110000110001 /
b110000110001 1
b110000110001 <
b110000110001 3
b110000110001 5
b1011110000 '
1#
#12
0#
#13
b111100100001 /
b111100100001 1
b111100100001 <
b111100100001 3
b111100100001 5
b0 =
0,
1"
08
b10010010111 !
b10010010111 +
b10010010111 9
b1000101110 2
b1000101110 %
b1000101110 *
b1000101110 0
b100100101110 :
b1000101110 '
1#
#14
0#
#15
b1010011011 2
b1010011011 %
b1010011011 *
b1010011011 0
0"
b1 =
1,
b111100100001 -
b111100100001 7
b111100100001 >
b1000101001111 /
b1000101001111 1
b1000101001111 <
b1000101001111 3
b1000101001111 5
b1010011011 '
1#
#16
0#
#17
b1001111101010 /
b1001111101010 1
b1001111101010 <
b1001111101010 3
b1001111101010 5
b0 =
0,
1"
18
b11001101001 !
b11001101001 +
b11001101001 9
b1000011101 2
b1000011101 %
b1000011101 *
b1000011101 0
b110011010010 :
b1000011101 '
1#
#18
0#
#19
b1010100001 2
b1010100001 %
b1010100001 *
b1010100001 0
0"
b1 =
1,
b1001111101010 -
b1001111101010 7
b1001111101010 >
b1011000000111 /
b1011000000111 1
b1011000000111 <
b1011000000111 3
b1011000000111 5
b1010100001 '
1#
#20
0#
#21
b1100010101000 /
b1100010101000 1
b1100010101000 <
b1100010101000 3
b1100010101000 5
b0 =
0,
1"
08
b10101011110 !
b10101011110 +
b10101011110 9
b1010011010 2
b1010011010 %
b1010011010 *
b1010011010 0
b101010111100 :
b1010011010 '
1#
#22
0#
#23
b1111000010 2
b1111000010 %
b1111000010 *
b1111000010 0
0"
b1 =
1,
b1100010101000 -
b1100010101000 7
b1100010101000 >
b1101101000010 /
b1101101000010 1
b1101101000010 <
b1101101000010 3
b1101101000010 5
b1111000010 '
1#
#24
0#
#25
b1111100000100 /
b1111100000100 1
b1111100000100 <
b1111100000100 3
b1111100000100 5
b0 =
0,
1"
18
b10011000011 !
b10011000011 +
b10011000011 9
b1110011001 2
b1110011001 %
b1110011001 *
b1110011001 0
b100110000111 :
b1110011001 '
1#
#26
0#
#27
b1110110101 2
b1110110101 %
b1110110101 *
b1110110101 0
0"
b1 =
1,
b1111100000100 -
b1111100000100 7
b1111100000100 >
b10001010011101 /
b10001010011101 1
b10001010011101 <
b10001010011101 3
b10001010011101 5
b1110110101 '
1#
#28
0#
#29
b10011001010010 /
b10011001010010 1
b10011001010010 <
b10011001010010 3
b10011001010010 5
b0 =
0,
1"
08
b10110001101 !
b10110001101 +
b10110001101 9
b1010010000 2
b1010010000 %
b1010010000 *
b1010010000 0
b101100011010 :
b1010010000 '
1#
#30
0#
#31
b1110111111 2
b1110111111 %
b1110111111 *
b1110111111 0
0"
b1 =
1,
b10011001010010 -
b10011001010010 7
b10011001010010 >
b10100011100010 /
b10100011100010 1
b10100011100010 <
b10100011100010 3
b10100011100010 5
b1110111111 '
1#
#32
0#
#33
b10110010100001 /
b10110010100001 1
b10110010100001 <
b10110010100001 3
b10110010100001 5
b0 =
0,
1"
18
b11011010101 !
b11011010101 +
b11011010101 9
b1110100111 2
b1110100111 %
b1110100111 *
b1110100111 0
b110110101010 :
b1110100111 '
1#
#34
0#
#35
b1010010100 2
b1010010100 %
b1010010100 *
b1010010100 0
0"
b1 =
1,
b10110010100001 -
b10110010100001 7
b10110010100001 >
b11000001001000 /
b11000001001000 1
b11000001001000 <
b11000001001000 3
b11000001001000 5
b1010010100 '
1#
#36
0#
#37
b11001011011100 /
b11001011011100 1
b11001011011100 <
b11001011011100 3
b11001011011100 5
b0 =
0,
1"
08
b11011001110 !
b11011001110 +
b11011001110 9
b1111001111 2
b1111001111 %
b1111001111 *
b1111001111 0
b110110011101 :
b1111001111 '
1#
#38
0#
#39
b1001101100 2
b1001101100 %
b1001101100 *
b1001101100 0
0"
b1 =
1,
b11001011011100 -
b11001011011100 7
b11001011011100 >
b11011010101011 /
b11011010101011 1
b11011010101011 <
b11011010101011 3
b11011010101011 5
b1001101100 '
1#
#40
0#
#41
b11100100010111 /
b11100100010111 1
b11100100010111 <
b11100100010111 3
b11100100010111 5
b0 =
0,
1"
18
b11001000101 !
b11001000101 +
b11001000101 9
b1011100010 2
b1011100010 %
b1011100010 *
b1011100010 0
b110010001010 :
b1011100010 '
1#
#42
0#
#43
b1001011111 2
b1001011111 %
b1001011111 *
b1001011111 0
0"
b1 =
1,
b11100100010111 -
b11100100010111 7
b11100100010111 >
b11101111111001 /
b11101111111001 1
b11101111111001 <
b11101111111001 3
b11101111111001 5
b1001011111 '
1#
#44
0#
#45
b11111001011000 /
b11111001011000 1
b11111001011000 <
b11111001011000 3
b11111001011000 5
b0 =
0,
1"
08
b11000111011 !
b11000111011 +
b11000111011 9
b1110001011 2
b1110001011 %
b1110001011 *
b1110001011 0
b110001110110 :
b1110001011 '
1#
#46
0#
#47
b1011000100 2
b1011000100 %
b1011000100 *
b1011000100 0
0"
b1 =
1,
b11111001011000 -
b11111001011000 7
b11111001011000 >
b100000111100011 /
b100000111100011 1
b100000111100011 <
b100000111100011 3
b100000111100011 5
b1011000100 '
1#
#48
0#
#49
b100010010100111 /
b100010010100111 1
b100010010100111 <
b100010010100111 3
b100010010100111 5
b0 =
0,
1"
18
b10110111110 !
b10110111110 +
b10110111110 9
b1110111101 2
b1110111101 %
b1110111101 *
b1110111101 0
b101101111100 :
b1110111101 '
1#
#50
0#
#51
b1111110000 2
b1111110000 %
b1111110000 *
b1111110000 0
0"
b1 =
1,
b100010010100111 -
b100010010100111 7
b100010010100111 >
b100100001100100 /
b100100001100100 1
b100100001100100 <
b100100001100100 3
b100100001100100 5
b1111110000 '
1#
#52
0#
#53
b100110001010100 /
b100110001010100 1
b100110001010100 <
b100110001010100 3
b100110001010100 5
b0 =
0,
1"
08
b10111001000 !
b10111001000 +
b10111001000 9
b1010011100 2
b1010011100 %
b1010011100 *
b1010011100 0
b101110010000 :
b1010011100 '
1#
#54
0#
#55
b1110010000 2
b1110010000 %
b1110010000 *
b1110010000 0
0"
b1 =
1,
b100110001010100 -
b100110001010100 7
b100110001010100 >
b100111011110000 /
b100111011110000 1
b100111011110000 <
b100111011110000 3
b100111011110000 5
b1110010000 '
1#
#56
0#
#57
b101001010000000 /
b101001010000000 1
b101001010000000 <
b101001010000000 3
b101001010000000 5
b0 =
0,
1"
18
b11011111110 !
b11011111110 +
b11011111110 9
b1100011110 2
b1100011110 %
b1100011110 *
b1100011110 0
b110111111100 :
b1100011110 '
1#
#58
0#
#59
b1001100010 2
b1001100010 %
b1001100010 *
b1001100010 0
0"
b1 =
1,
b101001010000000 -
b101001010000000 7
b101001010000000 >
b101010110011110 /
b101010110011110 1
b101010110011110 <
b101010110011110 3
b101010110011110 5
b1001100010 '
1#
#60
0#
#61
b101100000000000 /
b101100000000000 1
b101100000000000 <
b101100000000000 3
b101100000000000 5
b0 =
0,
1"
08
b11011101100 !
b11011101100 +
b11011101100 9
b1100001100 2
b1100001100 %
b1100001100 *
b1100001100 0
b110111011001 :
b1100001100 '
1#
#62
0#
#63
b1100010011 2
b1100010011 %
b1100010011 *
b1100010011 0
0"
b1 =
1,
b101100000000000 -
b101100000000000 7
b101100000000000 >
b101101100001100 /
b101101100001100 1
b101101100001100 <
b101101100001100 3
b101101100001100 5
b1100010011 '
1#
#64
0#
#65
b101111000011111 /
b101111000011111 1
b101111000011111 <
b101111000011111 3
b101111000011111 5
b0 =
0,
1"
18
b10111010110 !
b10111010110 +
b10111010110 9
b1111001010 2
b1111001010 %
b1111001010 *
b1111001010 0
b101110101100 :
b1111001010 '
1#
#66
0#
#67
b1010001111 2
b1010001111 %
b1010001111 *
b1010001111 0
0"
b1 =
1,
b101111000011111 -
b101111000011111 7
b101111000011111 >
b110000111101001 /
b110000111101001 1
b110000111101001 <
b110000111101001 3
b110000111101001 5
b1010001111 '
1#
#68
0#
#69
b110010001111000 /
b110010001111000 1
b110010001111000 <
b110010001111000 3
b110010001111000 5
b0 =
0,
1"
08
b10111001111 !
b10111001111 +
b10111001111 9
b1010000001 2
b1010000001 %
b1010000001 *
b1010000001 0
b101110011111 :
b1010000001 '
1#
#70
0#
#71
b1111111111 2
b1111111111 %
b1111111111 *
b1111111111 0
0"
b1 =
1,
b110010001111000 -
b110010001111000 7
b110010001111000 >
b110011011111001 /
b110011011111001 1
b110011011111001 <
b110011011111001 3
b110011011111001 5
b1111111111 '
1#
#72
0#
#73
b110101011111000 /
b110101011111000 1
b110101011111000 <
b110101011111000 3
b110101011111000 5
b0 =
0,
1"
18
b11000111100 !
b11000111100 +
b11000111100 9
b1010101110 2
b1010101110 %
b1010101110 *
b1010101110 0
b110001111000 :
b1010101110 '
1#
#74
0#
#75
b1111110101 2
b1111110101 %
b1111110101 *
b1111110101 0
0"
b1 =
1,
b110101011111000 -
b110101011111000 7
b110101011111000 >
b110110110100110 /
b110110110100110 1
b110110110100110 <
b110110110100110 3
b110110110100110 5
b1111110101 '
1#
#76
0#
#77
b111000110011011 /
b111000110011011 1
b111000110011011 <
b111000110011011 3
b111000110011011 5
b0 =
0,
1"
08
b11001101100 !
b11001101100 +
b11001101100 9
b1110010100 2
b1110010100 %
b1110010100 *
b1110010100 0
b110011011001 :
b1110010100 '
1#
#78
0#
#79
b1011001101 2
b1011001101 %
b1011001101 *
b1011001101 0
0"
b1 =
1,
b111000110011011 -
b111000110011011 7
b111000110011011 >
b111010100101111 /
b111010100101111 1
b111010100101111 <
b111010100101111 3
b111010100101111 5
b1011001101 '
1#
#80
0#
#81
b111011111111100 /
b111011111111100 1
b111011111111100 <
b111011111111100 3
b111011111111100 5
b0 =
0,
1"
18
b11010010001 !
b11010010001 +
b11010010001 9
b1100001000 2
b1100001000 %
b1100001000 *
b1100001000 0
b110100100011 :
b1100001000 '
1#
#82
0#
#83
b1111111111 2
b1111111111 %
b1111111111 *
b1111111111 0
0"
b1 =
1,
b111011111111100 -
b111011111111100 7
b111011111111100 >
b111101100000100 /
b111101100000100 1
b111101100000100 <
b111101100000100 3
b111101100000100 5
b1111111111 '
1#
#84
0#
#85
b111111100000011 /
b111111100000011 1
b111111100000011 <
b111111100000011 3
b111111100000011 5
b0 =
0,
1"
08
b11010000010 !
b11010000010 +
b11010000010 9
b1111010010 2
b1111010010 %
b1111010010 *
b1111010010 0
b110100000100 :
b1111010010 '
1#
#86
0#
#87
b1011110100 2
b1011110100 %
b1011110100 *
b1011110100 0
0"
b1 =
1,
b111111100000011 -
b111111100000011 7
b111111100000011 >
b1000001011010101 /
b1000001011010101 1
b1000001011010101 <
b1000001011010101 3
b1000001011010101 5
b1011110100 '
1#
#88
0#
#89
b1000010111001001 /
b1000010111001001 1
b1000010111001001 <
b1000010111001001 3
b1000010111001001 5
b0 =
0,
1"
18
b11010110100 !
b11010110100 +
b11010110100 9
b1010010101 2
b1010010101 %
b1010010101 *
b1010010101 0
b110101101000 :
b1010010101 '
1#
#90
0#
#91
b1111111111 2
b1111111111 %
b1111111111 *
b1111111111 0
0"
b1 =
1,
b1000010111001001 -
b1000010111001001 7
b1000010111001001 >
b1000100001011110 /
b1000100001011110 1
b1000100001011110 <
b1000100001011110 3
b1000100001011110 5
b1111111111 '
1#
#92
0#
#93
b1000110001011101 /
b1000110001011101 1
b1000110001011101 <
b1000110001011101 3
b1000110001011101 5
b0 =
0,
1"
08
b11011100110 !
b11011100110 +
b11011100110 9
b1010011111 2
b1010011111 %
b1010011111 *
b1010011111 0
b110111001101 :
b1010011111 '
1#
#94
0#
#95
b1110110100 2
b1110110100 %
b1110110100 *
b1110110100 0
0"
b1 =
1,
b1000110001011101 -
b1000110001011101 7
b1000110001011101 >
b1000111011111100 /
b1000111011111100 1
b1000111011111100 <
b1000111011111100 3
b1000111011111100 5
b1110110100 '
1#
#96
0#
#97
b1001001010110000 /
b1001001010110000 1
b1001001010110000 <
b1001001010110000 3
b1001001010110000 5
b0 =
0,
1"
18
b11010101101 !
b11010101101 +
b11010101101 9
b1011001011 2
b1011001011 %
b1011001011 *
b1011001011 0
b110101011010 :
b1011001011 '
1#
#98
0#
#99
b1111111111 2
b1111111111 %
b1111111111 *
b1111111111 0
0"
b1 =
1,
b1001001010110000 -
b1001001010110000 7
b1001001010110000 >
b1001010101111011 /
b1001010101111011 1
b1001010101111011 <
b1001010101111011 3
b1001010101111011 5
b1111111111 '
1#
#100
0#
#101
b1001100101111010 /
b1001100101111010 1
b1001100101111010 <
b1001100101111010 3
b1001100101111010 5
b0 =
0,
1"
08
b11001110011 !
b11001110011 +
b11001110011 9
b1100101110 2
b1100101110 %
b1100101110 *
b1100101110 0
b110011100111 :
b1100101110 '
1#
#102
0#
#103
b1101100010 2
b1101100010 %
b1101100010 *
b1101100010 0
0"
b1 =
1,
b1001100101111010 -
b1001100101111010 7
b1001100101111010 >
b1001110010101000 /
b1001110010101000 1
b1001110010101000 <
b1001110010101000 3
b1001110010101000 5
b1101100010 '
1#
#104
0#
#105
b1010000000001010 /
b1010000000001010 1
b1010000000001010 <
b1010000000001010 3
b1010000000001010 5
b0 =
0,
1"
18
b11010001110 !
b11010001110 +
b11010001110 9
b1111011011 2
b1111011011 %
b1111011011 *
b1111011011 0
b110100011101 :
b1111011011 '
1#
#106
0#
#107
b1111111111 2
b1111111111 %
b1111111111 *
b1111111111 0
0"
b1 =
1,
b1010000000001010 -
b1010000000001010 7
b1010000000001010 >
b1010001111100101 /
b1010001111100101 1
b1010001111100101 <
b1010001111100101 3
b1010001111100101 5
b1111111111 '
1#
#108
0#
#109
b1010011111100100 /
b1010011111100100 1
b1010011111100100 <
b1010011111100100 3
b1010011111100100 5
b0 =
0,
1"
08
b11010101101 !
b11010101101 +
b11010101101 9
b1100011010 2
b1100011010 %
b1100011010 *
b1100011010 0
b110101011010 :
b1100011010 '
1#
#110
0#
#111
b1111111111 2
b1111111111 %
b1111111111 *
b1111111111 0
0"
b1 =
1,
b1010011111100100 -
b1010011111100100 7
b1010011111100100 >
b1010101011111110 /
b1010101011111110 1
b1010101011111110 <
b1010101011111110 3
b1010101011111110 5
b1111111111 '
1#
#112
0#
#113
b1010111011111101 /
b1010111011111101 1
b1010111011111101 <
b1010111011111101 3
b1010111011111101 5
b0 =
0,
1"
18
b11100110101 !
b11100110101 +
b11100110101 9
b1111010100 2
b1111010100 %
b1111010100 *
b1111010100 0
b111001101010 :
b1111010100 '
1#
#114
0#
#115
b1111111111 2
b1111111111 %
b1111111111 *
b1111111111 0
0"
b1 =
1,
b1010111011111101 -
b1010111011111101 7
b1010111011111101 >
b1011001011010001 /
b1011001011010001 1
b1011001011010001 <
b1011001011010001 3
b1011001011010001 5
b1111111111 '
1#
#116
0#
#117
b1011011011010000 /
b1011011011010000 1
b1011011011010000 <
b1011011011010000 3
b1011011011010000 5
b0 =
0,
1"
08
b11101111001 !
b11101111001 +
b11101111001 9
b111011110011 :
1#
#118
0#
#119
b1100000110 2
b1100000110 %
b1100000110 *
b1100000110 0
0"
b1 =
1,
b1011011011010000 -
b1011011011010000 7
b1011011011010000 >
b1011101011001111 /
b1011101011001111 1
b1011101011001111 <
b1011101011001111 3
b1011101011001111 5
b1100000110 '
1#
#120
0#
#121
b1011110111010101 /
b1011110111010101 1
b1011110111010101 <
b1011110111010101 3
b1011110111010101 5
b0 =
0,
1"
18
b11101110110 !
b11101110110 +
b11101110110 9
b1100110101 2
b1100110101 %
b1100110101 *
b1100110101 0
b111011101100 :
b1100110101 '
1#
#122
0#
#123
b1111100001 2
b1111100001 %
b1111100001 *
b1111100001 0
0"
b1 =
1,
b1011110111010101 -
b1011110111010101 7
b1011110111010101 >
b1100000100001010 /
b1100000100001010 1
b1100000100001010 <
b1100000100001010 3
b1100000100001010 5
b1111100001 '
1#
#124
0#
#125
b1100010011101011 /
b1100010011101011 1
b1100010011101011 <
b1100010011101011 3
b1100010011101011 5
b0 =
0,
1"
08
b11101101100 !
b11101101100 +
b11101101100 9
b1111111111 2
b1111111111 %
b1111111111 *
b1111111111 0
b111011011000 :
b1111111111 '
1#
#126
0#
#127
b1101001101 2
b1101001101 %
b1101001101 *
b1101001101 0
0"
b1 =
1,
b1100010011101011 -
b1100010011101011 7
b1100010011101011 >
b1100100011101010 /
b1100100011101010 1
b1100100011101010 <
b1100100011101010 3
b1100100011101010 5
b1101001101 '
1#
#128
0#
#129
b1100110000110111 /
b1100110000110111 1
b1100110000110111 <
b1100110000110111 3
b1100110000110111 5
b0 =
0,
1"
18
b11100001101 !
b11100001101 +
b11100001101 9
b1111111111 2
b1111111111 %
b1111111111 *
b1111111111 0
b111000011011 :
b1111111111 '
1#
#130
0#
#131
b1100001010 2
b1100001010 %
b1100001010 *
b1100001010 0
0"
b1 =
1,
b1100110000110111 -
b1100110000110111 7
b1100110000110111 >
b1101000000110110 /
b1101000000110110 1
b1101000000110110 <
b1101000000110110 3
b1101000000110110 5
b1100001010 '
1#
#132
0#
#133
b1101001101000000 /
b1101001101000000 1
b1101001101000000 <
b1101001101000000 3
b1101001101000000 5
b0 =
0,
1"
08
b11100110001 !
b11100110001 +
b11100110001 9
b1111101110 2
b1111101110 %
b1111101110 *
b1111101110 0
b111001100010 :
b1111101110 '
1#
#134
0#
#135
b1011110010 2
b1011110010 %
b1011110010 *
b1011110010 0
0"
b1 =
1,
b1101001101000000 -
b1101001101000000 7
b1101001101000000 >
b1101011100101110 /
b1101011100101110 1
b1101011100101110 <
b1101011100101110 3
b1101011100101110 5
b1011110010 '
1#
#136
0#
#137
b1101101000100000 /
b1101101000100000 1
b1101101000100000 <
b1101101000100000 3
b1101101000100000 5
b0 =
0,
1"
18
b11100101010 !
b11100101010 +
b11100101010 9
b1111111111 2
b1111111111 %
b1111111111 *
b1111111111 0
b111001010101 :
b1111111111 '
1#
#138
0#
#139
0"
b1 =
1,
b1101101000100000 -
b1101101000100000 7
b1101101000100000 >
b1101111000011111 /
b1101111000011111 1
b1101111000011111 <
b1101111000011111 3
b1101111000011111 5
1#
#140
0#
#141
b1110001000011110 /
b1110001000011110 1
b1110001000011110 <
b1110001000011110 3
b1110001000011110 5
b0 =
0,
1"
08
b11011110100 !
b11011110100 +
b11011110100 9
b1110001111 2
b1110001111 %
b1110001111 *
b1110001111 0
b110111101001 :
b1110001111 '
1#
#142
0#
#143
b1111111111 2
b1111111111 %
b1111111111 *
b1111111111 0
0"
b1 =
1,
b1110001000011110 -
b1110001000011110 7
b1110001000011110 >
b1110010110101101 /
b1110010110101101 1
b1110010110101101 <
b1110010110101101 3
b1110010110101101 5
b1111111111 '
1#
#144
0#
#145
b1110100110101100 /
b1110100110101100 1
b1110100110101100 <
b1110100110101100 3
b1110100110101100 5
b0 =
0,
1"
18
b11101101111 !
b11101101111 +
b11101101111 9
b1110011000 2
b1110011000 %
b1110011000 *
b1110011000 0
b111011011110 :
b1110011000 '
1#
#146
0#
#147
b1111111111 2
b1111111111 %
b1111111111 *
b1111111111 0
0"
b1 =
1,
b1110100110101100 -
b1110100110101100 7
b1110100110101100 >
b1110110101000100 /
b1110110101000100 1
b1110110101000100 <
b1110110101000100 3
b1110110101000100 5
b1111111111 '
1#
#148
0#
#149
b1111000101000011 /
b1111000101000011 1
b1111000101000011 <
b1111000101000011 3
b1111000101000011 5
b0 =
0,
1"
08
b11111000110 !
b11111000110 +
b11111000110 9
b111110001100 :
1#
#150
0#
#151
0"
b1 =
1,
b1111000101000011 -
b1111000101000011 7
b1111000101000011 >
b1111010101000010 /
b1111010101000010 1
b1111010101000010 <
b1111010101000010 3
b1111010101000010 5
1#
#152
0#
#153
b1111100101000001 /
b1111100101000001 1
b1111100101000001 <
b1111100101000001 3
b1111100101000001 5
b0 =
0,
1"
18
b11110010010 !
b11110010010 +
b11110010010 9
b111100100101 :
1#
#154
0#
#155
0"
b1 =
1,
b1111100101000001 -
b1111100101000001 7
b1111100101000001 >
b1111110101000000 /
b1111110101000000 1
b1111110101000000 <
b1111110101000000 3
b1111110101000000 5
1#
#156
0#
