differentiator.v
module differentiator #(
    parameter N=2, 
    parameter BITS=10, 
    parameter N_BITS=$clog2(N)
) (
    input clk, 
    input rst, 
    input [BITS-1:0] stream_in, 
    input valid,
    output reg [BITS-1:0] stream_out, 
    output reg ready
);
    integer i;
    
    reg [BITS-1:0] buffer [N-1:0];
    reg [N_BITS-1:0] pointer;
    
    always @(posedge clk) begin
        if (rst) begin
            stream_out <= 0;
            pointer <= 0;
            ready <= 0;
            for (i = 0; i < N; i = i + 1) begin
                buffer[i] <= 0;
            end
        end else if (valid) begin
            stream_out <= stream_in - buffer[pointer];
            buffer[pointer] <= stream_in;
            pointer <= pointer + 1 == N ? 0 : pointer + 1;
            ready <= 1;
        end else begin
            ready <= 0;
        end
    end

endmodule

comb.v
module comb #(
    parameter M=1,
    parameter N=2,
    parameter BITS=10
) (
    input clk, 
    input rst, 
    input [BITS-1:0] stream_in, 
    input valid,
    output [BITS-1:0] stream_out, 
    output ready
);
    wire [BITS-1:0] data [M:0];
    wire handshake [M:0];

    genvar m;
    generate
        for (m = 0; m < M; m = m + 1) begin
            differentiator #(
                .N(N), 
                .BITS(BITS)
            ) dt (
                .clk(clk), 
                .rst(rst), 
                .stream_in(data[m]),
                .valid(handshake[m]),
                .stream_out(data[m + 1]),
                .ready(handshake[m + 1])
            );
        end
    endgenerate

    assign data[0] = stream_in;
    assign handshake[0] = valid;
    assign stream_out = data[M];
    assign ready = handshake[M];

endmodule

downsampler.v
module downsampler #(
    parameter N=2, 
    parameter BITS=10, 
    parameter N_BITS=$clog2(N)+1
) (
    input clk, 
    input rst,
    input [BITS-1:0] stream_in, 
    input valid,
    output reg [BITS-1:0] stream_out, 
    output reg ready
);
    reg [N_BITS-1:0] sample;
    
    always @(posedge clk) begin
        if (rst) begin
            sample <= 0;
            stream_out <= 0;
            ready <= 0;
        end 

        if (valid) begin
            if (sample == 0) begin
                stream_out <= stream_in;
                ready <= 1;
            end else ready <= 0;
            sample <= sample + 1 == N ? 0 : sample + 1;
        end else begin
            ready <= 0;
        end
    end
        
endmodule

integrator.v
module integrator #(
    parameter BITS=10
) (
    input clk, 
    input rst, 
    input [BITS-1:0] stream_in, 
    input valid,
    output [BITS-1:0] stream_out, 
    output reg ready
); 

    reg [BITS-1:0] buffer;

    always @(posedge clk) begin
        if (rst) begin
            buffer <= 0;
            ready <= 0;
        end else if (valid) begin
            buffer <= stream_in + buffer;
            ready <= 1;
        end
    end

    assign stream_out = buffer;

endmodule

accumulator.v
module accumulator #(
    parameter M=1,
    parameter BITS=10
) (
    input clk, 
    input rst, 
    input [BITS-1:0] stream_in, 
    input valid,
    output [BITS-1:0] stream_out, 
    output ready
);
    wire [BITS-1:0] data [M:0];
    wire handshake [M:0];

    genvar m;
    generate 
        for (m = 0; m < M; m = m + 1) begin
            integrator #(
                .BITS(BITS)
            ) it (
                .clk(clk), 
                .rst(rst), 
                .stream_in(data[m]),
                .valid(handshake[m]),
                .stream_out(data[m + 1]),
                .ready(handshake[m + 1])
            );
        end
    endgenerate

    assign data[0] = stream_in;
    assign handshake[0] = valid;
    assign stream_out = data[M];
    assign ready = handshake[M];

endmodule

CIC.v
module CIC #(
    parameter M=1, 
    parameter N=2, 
    parameter BITS=10,
    parameter N_BITS=$clog2(N)
) (
    input clk, 
    input rst, 
    input [BITS-1:0] stream_in, 
    input valid,
    output [BITS-1:0] stream_out, 
    output ready
);

    wire [BITS-1:0] accumulated;
    wire accumulated_ready;
    wire [BITS-1:0] downsampled;
    wire downsampled_ready;

    accumulator #(
        .M(M),
        .BITS(BITS)
    ) accumulator (
        .clk(clk),
        .rst(rst),
        .stream_in(stream_in),
        .valid(valid),
        .stream_out(accumulated),
        .ready(accumulated_ready)
    );

    downsampler #(
        .N(N),
        .BITS(BITS)
    ) downsampler (
        .clk(clk),
        .rst(rst),
        .stream_in(accumulated),
        .valid(accumulated_ready),
        .stream_out(downsampled),
        .ready(downsampled_ready)
    );

    differentiator #(
        .N(N),
        .BITS(BITS)
    ) differentiator (
        .clk(clk),
        .rst(rst),
        .stream_in(downsampled),
        .valid(downsampled_ready),
        .stream_out(stream_out),
        .ready(ready)
    );

endmodule

CIC_tb.v
`timescale 1ps/1ps

`define assert(signal, value) \
	if (signal != value) begin \
		$display("ASSERTION FAILED in %m: signal != value"); \
	end


module CIC_tb();

    localparam T = 2;
    localparam N = 2;
    localparam M = 1;
    localparam BITS = 16;

    integer fr, fw;

    reg clk = 0;
    reg rst = 0;
    reg [BITS-1:0] stream_in = 0;
    reg valid = 0;
    wire [BITS-1:0] stream_out;
    wire ready;

    reg [31:0] value = 0;

    CIC #(
        .M(M),
        .N(N),
        .BITS(BITS)
    ) DUT (
        .clk(clk),
        .rst(rst),
        .stream_in(stream_in),
        .valid(valid),
        .stream_out(stream_out),
        .ready(ready)
    );

    initial begin
        clk = 1'b0;
        forever #(T / 2) clk = ~clk;
    end

    initial begin
        rst = 1;
        valid = 0;
        repeat (2) @(posedge clk);
        rst = 0;
        valid = 1;
    end
    
    initial begin
        repeat (2) @(posedge clk)
        fr = $fopen("inputs.txt", "rb");
        while ($fscanf(fr, "%d\n", value)) begin
            stream_in <= value[9:0];
            @(posedge clk);
        end
    end

    initial begin
        repeat (2) @(posedge clk)
        fw = $fopen("outputs.txt", "w");
        while (1) begin
            if (ready) begin 
                $fwrite(fw, "%d\n", stream_out);
            end 
            @(posedge clk);
        end
    end

    initial begin
        $dumpfile("test.vcd");
        $dumpvars;
        #(2 * 1024 *T);
        $finish;
    end

endmodule

test.vcd
$date
	Wed Nov 16 10:52:32 2022
$end
$version
	Icarus Verilog
$end
$timescale
	1ps
$end
$scope module CIC_tb $end
$var wire 16 ! stream_out [15:0] $end
$var wire 1 " ready $end
$var reg 1 # clk $end
$var reg 1 $ rst $end
$var reg 16 % stream_in [15:0] $end
$var reg 1 & valid $end
$var reg 32 ' value [31:0] $end
$var integer 32 ( fr [31:0] $end
$var integer 32 ) fw [31:0] $end
$scope module DUT $end
$var wire 1 # clk $end
$var wire 1 $ rst $end
$var wire 16 * stream_in [15:0] $end
$var wire 1 & valid $end
$var wire 16 + stream_out [15:0] $end
$var wire 1 " ready $end
$var wire 1 , downsampled_ready $end
$var wire 16 - downsampled [15:0] $end
$var wire 1 . accumulated_ready $end
$var wire 16 / accumulated [15:0] $end
$scope module accumulator $end
$var wire 1 # clk $end
$var wire 1 . ready $end
$var wire 1 $ rst $end
$var wire 16 0 stream_in [15:0] $end
$var wire 16 1 stream_out [15:0] $end
$var wire 1 & valid $end
$scope begin genblk1[0] $end
$scope module it $end
$var wire 1 # clk $end
$var wire 1 $ rst $end
$var wire 16 2 stream_in [15:0] $end
$var wire 16 3 stream_out [15:0] $end
$var wire 1 4 valid $end
$var reg 16 5 buffer [15:0] $end
$var reg 1 6 ready $end
$upscope $end
$upscope $end
$upscope $end
$scope module differentiator $end
$var wire 1 # clk $end
$var wire 1 $ rst $end
$var wire 1 , valid $end
$var wire 16 7 stream_in [15:0] $end
$var reg 1 8 pointer $end
$var reg 1 " ready $end
$var reg 16 9 stream_out [15:0] $end
$var integer 32 : i [31:0] $end
$upscope $end
$scope module downsampler $end
$var wire 1 # clk $end
$var wire 1 $ rst $end
$var wire 16 ; stream_in [15:0] $end
$var wire 1 . valid $end
$var reg 1 , ready $end
$var reg 2 < sample [1:0] $end
$var reg 16 = stream_out [15:0] $end
$upscope $end
$upscope $end
$upscope $end
$scope module comb $end
$var wire 1 > clk $end
$var wire 1 ? ready $end
$var wire 1 @ rst $end
$var wire 10 A stream_in [9:0] $end
$var wire 10 B stream_out [9:0] $end
$var wire 1 C valid $end
$scope begin genblk1[0] $end
$scope module dt $end
$var wire 1 > clk $end
$var wire 1 @ rst $end
$var wire 10 D stream_in [9:0] $end
$var wire 1 E valid $end
$var reg 1 F pointer $end
$var reg 1 G ready $end
$var reg 10 H stream_out [9:0] $end
$var integer 32 I i [31:0] $end
$upscope $end
$upscope $end
$upscope $end
$enddefinitions $end
#0
$dumpvars
bx I
bx H
xG
xF
zE
bz D
zC
bx B
bz A
z@
x?
z>
bx =
bx <
bx ;
bx :
bx 9
x8
bx 7
x6
bx 5
04
bx 3
b0 2
bx 1
b0 0
bx /
x.
bx -
x,
bx +
b0 *
bx )
bx (
b0 '
0&
b0 %
1$
0#
x"
bx !
$end
#1
0.
06
b0 /
b0 1
b0 ;
b0 3
b0 5
0,
b0 -
b0 7
b0 =
b0 <
0"
08
b0 !
b0 +
b0 9
b10 :
b10000000000000000000000000000100 (
b10000000000000000000000000000011 )
1#
#2
0#
#3
b1010011000 2
b1010011000 %
b1010011000 *
b1010011000 0
b10000000000000000000000000000110 )
b1010011000 '
b10000000000000000000000000000101 (
14
1&
0$
b10 :
1#
#4
0#
#5
1.
16
b1010011000 /
b1010011000 1
b1010011000 ;
b1010011000 3
b1010011000 5
b1000100001 2
b1000100001 %
b1000100001 *
b1000100001 0
b1000100001 '
1#
#6
0#
#7
b1101100011 2
b1101100011 %
b1101100011 *
b1101100011 0
b1 <
1,
b1010011000 -
b1010011000 7
b1010011000 =
b10010111001 /
b10010111001 1
b10010111001 ;
b10010111001 3
b10010111001 5
b1101100011 '
1#
#8
0#
#9
b100000011100 /
b100000011100 1
b100000011100 ;
b100000011100 3
b100000011100 5
b0 <
0,
1"
18
b1010011000 !
b1010011000 +
b1010011000 9
b1101101010 2
b1101101010 %
b1101101010 *
b1101101010 0
b1101101010 '
1#
#10
0#
#11
b1111111111 2
b1111111111 %
b1111111111 *
b1111111111 0
0"
b1 <
1,
b100000011100 -
b100000011100 7
b100000011100 =
b101110000110 /
b101110000110 1
b101110000110 ;
b101110000110 3
b101110000110 5
b1111111111 '
1#
#12
0#
#13
b111110000101 /
b111110000101 1
b111110000101 ;
b111110000101 3
b111110000101 5
b0 <
0,
1"
08
b100000011100 !
b100000011100 +
b100000011100 9
b1001110100 2
b1001110100 %
b1001110100 *
b1001110100 0
b1001110100 '
1#
#14
0#
#15
b1100100100 2
b1100100100 %
b1100100100 *
b1100100100 0
0"
b1 <
1,
b111110000101 -
b111110000101 7
b111110000101 =
b1000111111001 /
b1000111111001 1
b1000111111001 ;
b1000111111001 3
b1000111111001 5
b1100100100 '
1#
#16
0#
#17
b1010100011101 /
b1010100011101 1
b1010100011101 ;
b1010100011101 3
b1010100011101 5
b0 <
0,
1"
18
b110011101101 !
b110011101101 +
b110011101101 9
b1000110011 2
b1000110011 %
b1000110011 *
b1000110011 0
b1000110011 '
1#
#18
0#
#19
b1110001001 2
b1110001001 %
b1110001001 *
b1110001001 0
0"
b1 <
1,
b1010100011101 -
b1010100011101 7
b1010100011101 =
b1011101010000 /
b1011101010000 1
b1011101010000 ;
b1011101010000 3
b1011101010000 5
b1110001001 '
1#
#20
0#
#21
b1101011011001 /
b1101011011001 1
b1101011011001 ;
b1101011011001 3
b1101011011001 5
b0 <
0,
1"
08
b110100000001 !
b110100000001 +
b110100000001 9
b1110000101 2
b1110000101 %
b1110000101 *
b1110000101 0
b1110000101 '
1#
#22
0#
#23
b1110010100 2
b1110010100 %
b1110010100 *
b1110010100 0
0"
b1 <
1,
b1101011011001 -
b1101011011001 7
b1101011011001 =
b1111001011110 /
b1111001011110 1
b1111001011110 ;
b1111001011110 3
b1111001011110 5
b1110010100 '
1#
#24
0#
#25
b10000111110010 /
b10000111110010 1
b10000111110010 ;
b10000111110010 3
b10000111110010 5
b0 <
0,
1"
18
b101101010100 !
b101101010100 +
b101101010100 9
b1010001000 2
b1010001000 %
b1010001000 *
b1010001000 0
b1010001000 '
1#
#26
0#
#27
b1111111111 2
b1111111111 %
b1111111111 *
b1111111111 0
0"
b1 <
1,
b10000111110010 -
b10000111110010 7
b10000111110010 =
b10010001111010 /
b10010001111010 1
b10010001111010 ;
b10010001111010 3
b10010001111010 5
b1111111111 '
1#
#28
0#
#29
b10100001111001 /
b10100001111001 1
b10100001111001 ;
b10100001111001 3
b10100001111001 5
b0 <
0,
1"
08
b110011010101 !
b110011010101 +
b110011010101 9
b1101101011 2
b1101101011 %
b1101101011 *
b1101101011 0
b1101101011 '
1#
#30
0#
#31
b1111111111 2
b1111111111 %
b1111111111 *
b1111111111 0
0"
b1 <
1,
b10100001111001 -
b10100001111001 7
b10100001111001 =
b10101111100100 /
b10101111100100 1
b10101111100100 ;
b10101111100100 3
b10101111100100 5
b1111111111 '
1#
#32
0#
#33
b10111111100011 /
b10111111100011 1
b10111111100011 ;
b10111111100011 3
b10111111100011 5
b0 <
0,
1"
18
b110110100000 !
b110110100000 +
b110110100000 9
b1111010010 2
b1111010010 %
b1111010010 *
b1111010010 0
b1111010010 '
1#
#34
0#
#35
b1111011110 2
b1111011110 %
b1111011110 *
b1111011110 0
0"
b1 <
1,
b10111111100011 -
b10111111100011 7
b10111111100011 =
b11001110110101 /
b11001110110101 1
b11001110110101 ;
b11001110110101 3
b11001110110101 5
b1111011110 '
1#
#36
0#
#37
b11011110010011 /
b11011110010011 1
b11011110010011 ;
b11011110010011 3
b11011110010011 5
b0 <
0,
1"
08
b110111110001 !
b110111110001 +
b110111110001 9
b1001100011 2
b1001100011 %
b1001100011 *
b1001100011 0
b1001100011 '
1#
#38
0#
#39
b1010001110 2
b1010001110 %
b1010001110 *
b1010001110 0
0"
b1 <
1,
b11011110010011 -
b11011110010011 7
b11011110010011 =
b11100111110110 /
b11100111110110 1
b11100111110110 ;
b11100111110110 3
b11100111110110 5
b1010001110 '
1#
#40
0#
#41
b11110010000100 /
b11110010000100 1
b11110010000100 ;
b11110010000100 3
b11110010000100 5
b0 <
0,
1"
18
b111100011010 !
b111100011010 +
b111100011010 9
b1100111010 2
b1100111010 %
b1100111010 *
b1100111010 0
b1100111010 '
1#
#42
0#
#43
b1111111111 2
b1111111111 %
b1111111111 *
b1111111111 0
0"
b1 <
1,
b11110010000100 -
b11110010000100 7
b11110010000100 =
b11111110111110 /
b11111110111110 1
b11111110111110 ;
b11111110111110 3
b11111110111110 5
b1111111111 '
1#
#44
0#
#45
b100001110111101 /
b100001110111101 1
b100001110111101 ;
b100001110111101 3
b100001110111101 5
b0 <
0,
1"
08
b110010100001 !
b110010100001 +
b110010100001 9
b1001010111 2
b1001010111 %
b1001010111 *
b1001010111 0
b1001010111 '
1#
#46
0#
#47
b1011010010 2
b1011010010 %
b1011010010 *
b1011010010 0
0"
b1 <
1,
b100001110111101 -
b100001110111101 7
b100001110111101 =
b100011000010100 /
b100011000010100 1
b100011000010100 ;
b100011000010100 3
b100011000010100 5
b1011010010 '
1#
#48
0#
#49
b100100011100110 /
b100100011100110 1
b100100011100110 ;
b100100011100110 3
b100100011100110 5
b0 <
0,
1"
18
b110000101010 !
b110000101010 +
b110000101010 9
b1111111111 2
b1111111111 %
b1111111111 *
b1111111111 0
b1111111111 '
1#
#50
0#
#51
b1010100011 2
b1010100011 %
b1010100011 *
b1010100011 0
0"
b1 <
1,
b100100011100110 -
b100100011100110 7
b100100011100110 =
b100110011100101 /
b100110011100101 1
b100110011100101 ;
b100110011100101 3
b100110011100101 5
b1010100011 '
1#
#52
0#
#53
b100111110001000 /
b100111110001000 1
b100111110001000 ;
b100111110001000 3
b100111110001000 5
b0 <
0,
1"
08
b110001100010 !
b110001100010 +
b110001100010 9
b1100111101 2
b1100111101 %
b1100111101 *
b1100111101 0
b1100111101 '
1#
#54
0#
#55
b1010001000 2
b1010001000 %
b1010001000 *
b1010001000 0
0"
b1 <
1,
b100111110001000 -
b100111110001000 7
b100111110001000 =
b101001011000101 /
b101001011000101 1
b101001011000101 ;
b101001011000101 3
b101001011000101 5
b1010001000 '
1#
#56
0#
#57
b101010101001101 /
b101010101001101 1
b101010101001101 ;
b101010101001101 3
b101010101001101 5
b0 <
0,
1"
18
b101111001011 !
b101111001011 +
b101111001011 9
b1011000001 2
b1011000001 %
b1011000001 *
b1011000001 0
b1011000001 '
1#
#58
0#
#59
b1110110110 2
b1110110110 %
b1110110110 *
b1110110110 0
0"
b1 <
1,
b101010101001101 -
b101010101001101 7
b101010101001101 =
b101100000001110 /
b101100000001110 1
b101100000001110 ;
b101100000001110 3
b101100000001110 5
b1110110110 '
1#
#60
0#
#61
b101101111000100 /
b101101111000100 1
b101101111000100 ;
b101101111000100 3
b101101111000100 5
b0 <
0,
1"
08
b110001100111 !
b110001100111 +
b110001100111 9
b1100001011 2
b1100001011 %
b1100001011 *
b1100001011 0
b1100001011 '
1#
#62
0#
#63
b1111010011 2
b1111010011 %
b1111010011 *
b1111010011 0
0"
b1 <
1,
b101101111000100 -
b101101111000100 7
b101101111000100 =
b101111011001111 /
b101111011001111 1
b101111011001111 ;
b101111011001111 3
b101111011001111 5
b1111010011 '
1#
#64
0#
#65
b110001010100010 /
b110001010100010 1
b110001010100010 ;
b110001010100010 3
b110001010100010 5
b0 <
0,
1"
18
b110000111100 !
b110000111100 +
b110000111100 9
b1100111011 2
b1100111011 %
b1100111011 *
b1100111011 0
b1100111011 '
1#
#66
0#
#67
b1111111111 2
b1111111111 %
b1111111111 *
b1111111111 0
0"
b1 <
1,
b110001010100010 -
b110001010100010 7
b110001010100010 =
b110010111011101 /
b110010111011101 1
b110010111011101 ;
b110010111011101 3
b110010111011101 5
b1111111111 '
1#
#68
0#
#69
b110100111011100 /
b110100111011100 1
b110100111011100 ;
b110100111011100 3
b110100111011100 5
b0 <
0,
1"
08
b110101010101 !
b110101010101 +
b110101010101 9
b1100011001 2
b1100011001 %
b1100011001 *
b1100011001 0
b1100011001 '
1#
#70
0#
#71
b1111111111 2
b1111111111 %
b1111111111 *
b1111111111 0
0"
b1 <
1,
b110100111011100 -
b110100111011100 7
b110100111011100 =
b110110011110101 /
b110110011110101 1
b110110011110101 ;
b110110011110101 3
b110110011110101 5
b1111111111 '
1#
#72
0#
#73
b111000011110100 /
b111000011110100 1
b111000011110100 ;
b111000011110100 3
b111000011110100 5
b0 <
0,
1"
18
b111000011000 !
b111000011000 +
b111000011000 9
b1110110110 2
b1110110110 %
b1110110110 *
b1110110110 0
b1110110110 '
1#
#74
0#
#75
b1100101001 2
b1100101001 %
b1100101001 *
b1100101001 0
0"
b1 <
1,
b111000011110100 -
b111000011110100 7
b111000011110100 =
b111010010101010 /
b111010010101010 1
b111010010101010 ;
b111010010101010 3
b111010010101010 5
b1100101001 '
1#
#76
0#
#77
b111011111010011 /
b111011111010011 1
b111011111010011 ;
b111011111010011 3
b111011111010011 5
b0 <
0,
1"
08
b111001010010 !
b111001010010 +
b111001010010 9
b1111010100 2
b1111010100 %
b1111010100 *
b1111010100 0
b1111010100 '
1#
#78
0#
#79
b1111111111 2
b1111111111 %
b1111111111 *
b1111111111 0
0"
b1 <
1,
b111011111010011 -
b111011111010011 7
b111011111010011 =
b111101110100111 /
b111101110100111 1
b111101110100111 ;
b111101110100111 3
b111101110100111 5
b1111111111 '
1#
#80
0#
#81
b111111110100110 /
b111111110100110 1
b111111110100110 ;
b111111110100110 3
b111111110100110 5
b0 <
0,
1"
18
b110111110111 !
b110111110111 +
b110111110111 9
b1010000110 2
b1010000110 %
b1010000110 *
b1010000110 0
b1010000110 '
1#
#82
0#
#83
b1100011010 2
b1100011010 %
b1100011010 *
b1100011010 0
0"
b1 <
1,
b111111110100110 -
b111111110100110 7
b111111110100110 =
b1000001000101100 /
b1000001000101100 1
b1000001000101100 ;
b1000001000101100 3
b1000001000101100 5
b1100011010 '
1#
#84
0#
#85
b1000010101000110 /
b1000010101000110 1
b1000010101000110 ;
b1000010101000110 3
b1000010101000110 5
b0 <
0,
1"
08
b111010110010 !
b111010110010 +
b111010110010 9
b1011110011 2
b1011110011 %
b1011110011 *
b1011110011 0
b1011110011 '
1#
#86
0#
#87
b1011010111 2
b1011010111 %
b1011010111 *
b1011010111 0
0"
b1 <
1,
b1000010101000110 -
b1000010101000110 7
b1000010101000110 =
b1000100000111001 /
b1000100000111001 1
b1000100000111001 ;
b1000100000111001 3
b1000100000111001 5
b1011010111 '
1#
#88
0#
#89
b1000101100010000 /
b1000101100010000 1
b1000101100010000 ;
b1000101100010000 3
b1000101100010000 5
b0 <
0,
1"
18
b110101110011 !
b110101110011 +
b110101110011 9
b1111001101 2
b1111001101 %
b1111001101 *
b1111001101 0
b1111001101 '
1#
#90
0#
#91
b1100001101 2
b1100001101 %
b1100001101 *
b1100001101 0
0"
b1 <
1,
b1000101100010000 -
b1000101100010000 7
b1000101100010000 =
b1000111011011101 /
b1000111011011101 1
b1000111011011101 ;
b1000111011011101 3
b1000111011011101 5
b1100001101 '
1#
#92
0#
#93
b1001000111101010 /
b1001000111101010 1
b1001000111101010 ;
b1001000111101010 3
b1001000111101010 5
b0 <
0,
1"
08
b101101101010 !
b101101101010 +
b101101101010 9
b1100001111 2
b1100001111 %
b1100001111 *
b1100001111 0
b1100001111 '
1#
#94
0#
#95
b1110011111 2
b1110011111 %
b1110011111 *
b1110011111 0
0"
b1 <
1,
b1001000111101010 -
b1001000111101010 7
b1001000111101010 =
b1001010011111001 /
b1001010011111001 1
b1001010011111001 ;
b1001010011111001 3
b1001010011111001 5
b1110011111 '
1#
#96
0#
#97
b1001100010011000 /
b1001100010011000 1
b1001100010011000 ;
b1001100010011000 3
b1001100010011000 5
b0 <
0,
1"
18
b110010100100 !
b110010100100 +
b110010100100 9
b1010010011 2
b1010010011 %
b1010010011 *
b1010010011 0
b1010010011 '
1#
#98
0#
#99
b1010011101 2
b1010011101 %
b1010011101 *
b1010011101 0
0"
b1 <
1,
b1001100010011000 -
b1001100010011000 7
b1001100010011000 =
b1001101100101011 /
b1001101100101011 1
b1001101100101011 ;
b1001101100101011 3
b1001101100101011 5
b1010011101 '
1#
#100
0#
#101
b1001110111001000 /
b1001110111001000 1
b1001110111001000 ;
b1001110111001000 3
b1001110111001000 5
b0 <
0,
1"
08
b110110001000 !
b110110001000 +
b110110001000 9
b1111111111 2
b1111111111 %
b1111111111 *
b1111111111 0
b1111111111 '
1#
#102
0#
#103
0"
b1 <
1,
b1001110111001000 -
b1001110111001000 7
b1001110111001000 =
b1010000111000111 /
b1010000111000111 1
b1010000111000111 ;
b1010000111000111 3
b1010000111000111 5
1#
#104
0#
#105
b1010010111000110 /
b1010010111000110 1
b1010010111000110 ;
b1010010111000110 3
b1010010111000110 5
b0 <
0,
1"
18
b101111011110 !
b101111011110 +
b101111011110 9
b1010111000 2
b1010111000 %
b1010111000 *
b1010111000 0
b1010111000 '
1#
#106
0#
#107
b1101011110 2
b1101011110 %
b1101011110 *
b1101011110 0
0"
b1 <
1,
b1010010111000110 -
b1010010111000110 7
b1010010111000110 =
b1010100001111110 /
b1010100001111110 1
b1010100001111110 ;
b1010100001111110 3
b1010100001111110 5
b1101011110 '
1#
#108
0#
#109
b1010101111011100 /
b1010101111011100 1
b1010101111011100 ;
b1010101111011100 3
b1010101111011100 5
b0 <
0,
1"
08
b110100101110 !
b110100101110 +
b110100101110 9
b1111111111 2
b1111111111 %
b1111111111 *
b1111111111 0
b1111111111 '
1#
#110
0#
#111
b1101100111 2
b1101100111 %
b1101100111 *
b1101100111 0
0"
b1 <
1,
b1010101111011100 -
b1010101111011100 7
b1010101111011100 =
b1010111111011011 /
b1010111111011011 1
b1010111111011011 ;
b1010111111011011 3
b1010111111011011 5
b1101100111 '
1#
#112
0#
#113
b1011001101000010 /
b1011001101000010 1
b1011001101000010 ;
b1011001101000010 3
b1011001101000010 5
b0 <
0,
1"
18
b111000010100 !
b111000010100 +
b111000010100 9
b1111111111 2
b1111111111 %
b1111111111 *
b1111111111 0
b1111111111 '
1#
#114
0#
#115
b1101011110 2
b1101011110 %
b1101011110 *
b1101011110 0
0"
b1 <
1,
b1011001101000010 -
b1011001101000010 7
b1011001101000010 =
b1011011101000001 /
b1011011101000001 1
b1011011101000001 ;
b1011011101000001 3
b1011011101000001 5
b1101011110 '
1#
#116
0#
#117
b1011101010011111 /
b1011101010011111 1
b1011101010011111 ;
b1011101010011111 3
b1011101010011111 5
b0 <
0,
1"
08
b110101111100 !
b110101111100 +
b110101111100 9
b1111111111 2
b1111111111 %
b1111111111 *
b1111111111 0
b1111111111 '
1#
#118
0#
#119
b1111101110 2
b1111101110 %
b1111101110 *
b1111101110 0
0"
b1 <
1,
b1011101010011111 -
b1011101010011111 7
b1011101010011111 =
b1011111010011110 /
b1011111010011110 1
b1011111010011110 ;
b1011111010011110 3
b1011111010011110 5
b1111101110 '
1#
#120
0#
#121
b1100001010001100 /
b1100001010001100 1
b1100001010001100 ;
b1100001010001100 3
b1100001010001100 5
b0 <
0,
1"
18
b111011000011 !
b111011000011 +
b111011000011 9
b1011010101 2
b1011010101 %
b1011010101 *
b1011010101 0
b1011010101 '
1#
#122
0#
#123
b1101110010 2
b1101110010 %
b1101110010 *
b1101110010 0
0"
b1 <
1,
b1100001010001100 -
b1100001010001100 7
b1100001010001100 =
b1100010101100001 /
b1100010101100001 1
b1100010101100001 ;
b1100010101100001 3
b1100010101100001 5
b1101110010 '
1#
#124
0#
#125
b1100100011010011 /
b1100100011010011 1
b1100100011010011 ;
b1100100011010011 3
b1100100011010011 5
b0 <
0,
1"
08
b111101001010 !
b111101001010 +
b111101001010 9
b1100110100 2
b1100110100 %
b1100110100 *
b1100110100 0
b1100110100 '
1#
#126
0#
#127
b1100111000 2
b1100111000 %
b1100111000 *
b1100111000 0
0"
b1 <
1,
b1100100011010011 -
b1100100011010011 7
b1100100011010011 =
b1100110000000111 /
b1100110000000111 1
b1100110000000111 ;
b1100110000000111 3
b1100110000000111 5
b1100111000 '
1#
#128
0#
#129
b1100111100111111 /
b1100111100111111 1
b1100111100111111 ;
b1100111100111111 3
b1100111100111111 5
b0 <
0,
1"
18
b111000110100 !
b111000110100 +
b111000110100 9
b1111111111 2
b1111111111 %
b1111111111 *
b1111111111 0
b1111111111 '
1#
#130
0#
#131
0"
b1 <
1,
b1100111100111111 -
b1100111100111111 7
b1100111100111111 =
b1101001100111110 /
b1101001100111110 1
b1101001100111110 ;
b1101001100111110 3
b1101001100111110 5
1#
#132
0#
#133
b1101011100111101 /
b1101011100111101 1
b1101011100111101 ;
b1101011100111101 3
b1101011100111101 5
b0 <
0,
1"
08
b110010110011 !
b110010110011 +
b110010110011 9
b1011100000 2
b1011100000 %
b1011100000 *
b1011100000 0
b1011100000 '
1#
#134
0#
#135
b1101000010 2
b1101000010 %
b1101000010 *
b1101000010 0
0"
b1 <
1,
b1101011100111101 -
b1101011100111101 7
b1101011100111101 =
b1101101000011101 /
b1101101000011101 1
b1101101000011101 ;
b1101101000011101 3
b1101101000011101 5
b1101000010 '
1#
#136
0#
#137
b1101110101011111 /
b1101110101011111 1
b1101110101011111 ;
b1101110101011111 3
b1101110101011111 5
b0 <
0,
1"
18
b111001101010 !
b111001101010 +
b111001101010 9
b1111111111 2
b1111111111 %
b1111111111 *
b1111111111 0
b1111111111 '
1#
#138
0#
#139
0"
b1 <
1,
b1101110101011111 -
b1101110101011111 7
b1101110101011111 =
b1110000101011110 /
b1110000101011110 1
b1110000101011110 ;
b1110000101011110 3
b1110000101011110 5
1#
#140
0#
#141
b1110010101011101 /
b1110010101011101 1
b1110010101011101 ;
b1110010101011101 3
b1110010101011101 5
b0 <
0,
1"
08
b111000100000 !
b111000100000 +
b111000100000 9
b1101000000 2
b1101000000 %
b1101000000 *
b1101000000 0
b1101000000 '
1#
#142
0#
#143
b1111000101 2
b1111000101 %
b1111000101 *
b1111000101 0
0"
b1 <
1,
b1110010101011101 -
b1110010101011101 7
b1110010101011101 =
b1110100010011101 /
b1110100010011101 1
b1110100010011101 ;
b1110100010011101 3
b1110100010011101 5
b1111000101 '
1#
#144
0#
#145
b1110110001100010 /
b1110110001100010 1
b1110110001100010 ;
b1110110001100010 3
b1110110001100010 5
b0 <
0,
1"
18
b1111111111 2
b1111111111 %
b1111111111 *
b1111111111 0
b1111111111 '
1#
#146
0#
#147
b1101011110 2
b1101011110 %
b1101011110 *
b1101011110 0
0"
b1 <
1,
b1110110001100010 -
b1110110001100010 7
b1110110001100010 =
b1111000001100001 /
b1111000001100001 1
b1111000001100001 ;
b1111000001100001 3
b1111000001100001 5
b1101011110 '
1#
#148
0#
#149
b1111001110111111 /
b1111001110111111 1
b1111001110111111 ;
b1111001110111111 3
b1111001110111111 5
b0 <
0,
1"
08
b111100000011 !
b111100000011 +
b111100000011 9
b1111111111 2
b1111111111 %
b1111111111 *
b1111111111 0
b1111111111 '
1#
#150
0#
#151
b1100010101 2
b1100010101 %
b1100010101 *
b1100010101 0
0"
b1 <
1,
b1111001110111111 -
b1111001110111111 7
b1111001110111111 =
b1111011110111110 /
b1111011110111110 1
b1111011110111110 ;
b1111011110111110 3
b1111011110111110 5
b1100010101 '
1#
#152
0#
#153
b1111101011010011 /
b1111101011010011 1
b1111101011010011 ;
b1111101011010011 3
b1111101011010011 5
b0 <
0,
1"
18
b111001100010 !
b111001100010 +
b111001100010 9
b1111111111 2
b1111111111 %
b1111111111 *
b1111111111 0
b1111111111 '
1#
#154
0#
#155
b1101111110 2
b1101111110 %
b1101111110 *
b1101111110 0
0"
b1 <
1,
b1111101011010011 -
b1111101011010011 7
b1111101011010011 =
b1111111011010010 /
b1111111011010010 1
b1111111011010010 ;
b1111111011010010 3
b1111111011010010 5
b1101111110 '
1#
#156
0#
#157
b1001010000 /
b1001010000 1
b1001010000 ;
b1001010000 3
b1001010000 5
b0 <
0,
1"
08
b111001110001 !
b111001110001 +
b111001110001 9
b1100100110 2
b1100100110 %
b1100100110 *
b1100100110 0
b1100100110 '
1#
#158
0#
#159
b1111101110 2
b1111101110 %
b1111101110 *
b1111101110 0
0"
b1 <
1,
b1001010000 -
b1001010000 7
b1001010000 =
b10101110110 /
b10101110110 1
b10101110110 ;
b10101110110 3
b10101110110 5
b1111101110 '
1#
#160
0#
